[{"created_at":"Mon Mar 18 14:09:04 +0000 2013","id":313653281350111232,"id_str":"313653281350111232","text":"thx for the follow @ecoalsur The First Green App for traveling throughout Latin America.","source":"web","truncated":false,"in_reply_to_status_id":null,"in_reply_to_status_id_str":null,"in_reply_to_user_id":null,"in_reply_to_user_id_str":null,"in_reply_to_screen_name":null,"user":{"id":253595500,"id_str":"253595500","name":"Byron Shirto","screen_name":"TalkingStickMkt","location":"Cheltenham, UK","description":"Luxury tourism marketing, representation & PR in the United Kingdom and Europe\r\n","url":"http:\/\/www.talkingstickmktg.com","entities":{"url":{"urls":[{"url":"http:\/\/www.talkingstickmktg.com","expanded_url":null,"indices":[0,31]}]},"description":{"urls":[]}},"protected":false,"followers_count":82,"friends_count":90,"listed_count":3,"created_at":"Thu Feb 17 15:31:24 +0000 2011","favourites_count":1,"utc_offset":null,"time_zone":null,"geo_enabled":false,"verified":false,"statuses_count":172,"lang":"en","contributors_enabled":false,"is_translator":false,"profile_background_color":"C0DEED","profile_background_image_url":"http:\/\/a0.twimg.com\/images\/themes\/theme1\/bg.png","profile_background_image_url_https":"https:\/\/si0.twimg.com\/images\/themes\/theme1\/bg.png","profile_background_tile":false,"profile_image_url":"http:\/\/a0.twimg.com\/profile_images\/2986322725\/356222fa12c61b9f23957abf27e4d013_normal.png","profile_image_url_https":"https:\/\/si0.twimg.com\/profile_images\/2986322725\/356222fa12c61b9f23957abf27e4d013_normal.png","profile_link_color":"0084B4","profile_sidebar_border_color":"C0DEED","profile_sidebar_fill_color":"DDEEF6","profile_text_color":"333333","profile_use_background_image":true,"default_profile":true,"default_profile_image":false,"following":null,"follow_request_sent":false,"notifications":null},"geo":null,"coordinates":null,"place":null,"contributors":null,"retweet_count":0,"favorite_count":0,"entities":{"hashtags":[],"urls":[],"user_mentions":[{"screen_name":"ecoalsur","name":"Ecoalsur","id":570017669,"id_str":"570017669","indices":[19,28]}]},"favorited":false,"retweeted":false,"lang":"en"},{"created_at":"Mon Mar 11 18:07:17 +0000 2013","id":311176516371361792,"id_str":"311176516371361792","text":"#Brazil plans to control hotel rates during #FIFA World Cup #tourism http:\/\/t.co\/eMzd8OzyHb","source":"web","truncated":false,"in_reply_to_status_id":null,"in_reply_to_status_id_str":null,"in_reply_to_user_id":null,"in_reply_to_user_id_str":null,"in_reply_to_screen_name":null,"user":{"id":253595500,"id_str":"253595500","name":"Byron Shirto","screen_name":"TalkingStickMkt","location":"Cheltenham, UK","description":"Luxury tourism marketing, representation & PR in the United Kingdom and Europe\r\n","url":"http:\/\/www.talkingstickmktg.com","entities":{"url":{"urls":[{"url":"http:\/\/www.talkingstickmktg.com","expanded_url":null,"indices":[0,31]}]},"description":{"urls":[]}},"protected":false,"followers_count":82,"friends_count":90,"listed_count":3,"created_at":"Thu Feb 17 15:31:24 +0000 2011","favourites_count":1,"utc_offset":null,"time_zone":null,"geo_enabled":false,"verified":false,"statuses_count":172,"lang":"en","contributors_enabled":false,"is_translator":false,"profile_background_color":"C0DEED","profile_background_image_url":"http:\/\/a0.twimg.com\/images\/themes\/theme1\/bg.png","profile_background_image_url_https":"https:\/\/si0.twimg.com\/images\/themes\/theme1\/bg.png","profile_background_tile":false,"profile_image_url":"http:\/\/a0.twimg.com\/profile_images\/2986322725\/356222fa12c61b9f23957abf27e4d013_normal.png","profile_image_url_https":"https:\/\/si0.twimg.com\/profile_images\/2986322725\/356222fa12c61b9f23957abf27e4d013_normal.png","profile_link_color":"0084B4","profile_sidebar_border_color":"C0DEED","profile_sidebar_fill_color":"DDEEF6","profile_text_color":"333333","profile_use_background_image":true,"default_profile":true,"default_profile_image":false,"following":null,"follow_request_sent":false,"notifications":null},"geo":null,"coordinates":null,"place":null,"contributors":null,"retweet_count":0,"favorite_count":0,"entities":{"hashtags":[{"text":"Brazil","indices":[0,7]},{"text":"FIFA","indices":[44,49]},{"text":"tourism","indices":[60,68]}],"urls":[{"url":"http:\/\/t.co\/eMzd8OzyHb","expanded_url":"http:\/\/bit.ly\/X02afi","display_url":"bit.ly\/X02afi","indices":[69,91]}],"user_mentions":[]},"favorited":false,"retweeted":false,"possibly_sensitive":false,"lang":"en"},{"created_at":"Mon Mar 11 18:02:24 +0000 2013","id":311175286681133058,"id_str":"311175286681133058","text":"#Panama in #LatinAmerica is the rising star according to #Tourism Competitiveness Report 2013 covering 140 countries http:\/\/t.co\/hwCMIoFNSB","source":"web","truncated":false,"in_reply_to_status_id":null,"in_reply_to_status_id_str":null,"in_reply_to_user_id":null,"in_reply_to_user_id_str":null,"in_reply_to_screen_name":null,"user":{"id":253595500,"id_str":"253595500","name":"Byron Shirto","screen_name":"TalkingStickMkt","location":"Cheltenham, UK","description":"Luxury tourism marketing, representation & PR in the United Kingdom and Europe\r\n","url":"http:\/\/www.talkingstickmktg.com","entities":{"url":{"urls":[{"url":"http:\/\/www.talkingstickmktg.com","expanded_url":null,"indices":[0,31]}]},"description":{"urls":[]}},"protected":false,"followers_count":82,"friends_count":90,"listed_count":3,"created_at":"Thu Feb 17 15:31:24 +0000 2011","favourites_count":1,"utc_offset":null,"time_zone":null,"geo_enabled":false,"verified":false,"statuses_count":172,"lang":"en","contributors_enabled":false,"is_translator":false,"profile_background_color":"C0DEED","profile_background_image_url":"http:\/\/a0.twimg.com\/images\/themes\/theme1\/bg.png","profile_background_image_url_https":"https:\/\/si0.twimg.com\/images\/themes\/theme1\/bg.png","profile_background_tile":false,"profile_image_url":"http:\/\/a0.twimg.com\/profile_images\/2986322725\/356222fa12c61b9f23957abf27e4d013_normal.png","profile_image_url_https":"https:\/\/si0.twimg.com\/profile_images\/2986322725\/356222fa12c61b9f23957abf27e4d013_normal.png","profile_link_color":"0084B4","profile_sidebar_border_color":"C0DEED","profile_sidebar_fill_color":"DDEEF6","profile_text_color":"333333","profile_use_background_image":true,"default_profile":true,"default_profile_image":false,"following":null,"follow_request_sent":false,"notifications":null},"geo":null,"coordinates":null,"place":null,"contributors":null,"retweet_count":0,"favorite_count":0,"entities":{"hashtags":[{"text":"Panama","indices":[0,7]},{"text":"LatinAmerica","indices":[11,24]},{"text":"Tourism","indices":[57,65]}],"urls":[{"url":"http:\/\/t.co\/hwCMIoFNSB","expanded_url":"http:\/\/bit.ly\/14L6ZfP","display_url":"bit.ly\/14L6ZfP","indices":[117,139]}],"user_mentions":[]},"favorited":false,"retweeted":false,"possibly_sensitive":false,"lang":"en"},{"created_at":"Fri Mar 01 10:55:55 +0000 2013","id":307444081401950208,"id_str":"307444081401950208","text":"Good luck all @LasVerandas luxury hotel #Roatan #Honduras on your soft opening TODAY. Look forward to visiting soon. #travel #Caribbean","source":"web","truncated":false,"in_reply_to_status_id":null,"in_reply_to_status_id_str":null,"in_reply_to_user_id":null,"in_reply_to_user_id_str":null,"in_reply_to_screen_name":null,"user":{"id":253595500,"id_str":"253595500","name":"Byron Shirto","screen_name":"TalkingStickMkt","location":"Cheltenham, UK","description":"Luxury tourism marketing, representation & PR in the United Kingdom and Europe\r\n","url":"http:\/\/www.talkingstickmktg.com","entities":{"url":{"urls":[{"url":"http:\/\/www.talkingstickmktg.com","expanded_url":null,"indices":[0,31]}]},"description":{"urls":[]}},"protected":false,"followers_count":82,"friends_count":90,"listed_count":3,"created_at":"Thu Feb 17 15:31:24 +0000 2011","favourites_count":1,"utc_offset":null,"time_zone":null,"geo_enabled":false,"verified":false,"statuses_count":172,"lang":"en","contributors_enabled":false,"is_translator":false,"profile_background_color":"C0DEED","profile_background_image_url":"http:\/\/a0.twimg.com\/images\/themes\/theme1\/bg.png","profile_background_image_url_https":"https:\/\/si0.twimg.com\/images\/themes\/theme1\/bg.png","profile_background_tile":false,"profile_image_url":"http:\/\/a0.twimg.com\/profile_images\/2986322725\/356222fa12c61b9f23957abf27e4d013_normal.png","profile_image_url_https":"https:\/\/si0.twimg.com\/profile_images\/2986322725\/356222fa12c61b9f23957abf27e4d013_normal.png","profile_link_color":"0084B4","profile_sidebar_border_color":"C0DEED","profile_sidebar_fill_color":"DDEEF6","profile_text_color":"333333","profile_use_background_image":true,"default_profile":true,"default_profile_image":false,"following":null,"follow_request_sent":false,"notifications":null},"geo":null,"coordinates":null,"place":null,"contributors":null,"retweet_count":1,"favorite_count":0,"entities":{"hashtags":[{"text":"Roatan","indices":[40,47]},{"text":"Honduras","indices":[48,57]},{"text":"travel","indices":[117,124]},{"text":"Caribbean","indices":[125,135]}],"urls":[],"user_mentions":[{"screen_name":"LasVerandas","name":"Las Verandas","id":1148552107,"id_str":"1148552107","indices":[14,26]}]},"favorited":false,"retweeted":false,"lang":"en"}]